td_cli-2.3.0.dist-info/licenses/LICENSE
todo/__init__.py
todo/__main__.py
todo/constants.py
todo/exceptions.py
todo/settings.py
todo/commands/__init__.py
todo/commands/base.py
todo/commands/config/__init__.py
todo/commands/config/initialize.py
todo/commands/group/__init__.py
todo/commands/group/add.py
todo/commands/group/delete.py
todo/commands/group/edit.py
todo/commands/group/get.py
todo/commands/group/list.py
todo/commands/group/preset.py
todo/commands/todo/__init__.py
todo/commands/todo/add.py
todo/commands/todo/complete.py
todo/commands/todo/count.py
todo/commands/todo/delete.py
todo/commands/todo/edit.py
todo/commands/todo/get.py
todo/commands/todo/list.py
todo/commands/todo/list_interactive.py
todo/commands/todo/uncomplete.py
todo/parser/__init__.py
todo/parser/base.py
todo/parser/subparsers/__init__.py
todo/parser/subparsers/add_group.py
todo/parser/subparsers/add_todo.py
todo/parser/subparsers/count_todos.py
todo/parser/subparsers/group.py
todo/parser/subparsers/initialize_config.py
todo/parser/subparsers/list_groups.py
todo/parser/subparsers/list_todos.py
todo/parser/subparsers/todo.py
todo/renderers/__init__.py
todo/renderers/base.py
todo/renderers/render_error.py
todo/renderers/render_help.py
todo/renderers/render_input.py
todo/renderers/render_output.py
todo/renderers/render_output_with_textwrap.py
todo/renderers/styles/__init__.py
todo/renderers/styles/ansi_fore.py
todo/renderers/styles/ansi_style.py
todo/renderers/styles/base.py
todo/services/__init__.py
todo/services/base.py
todo/services/group.py
todo/services/todo.py
todo/utils/__init__.py
todo/utils/menu/__init__.py
todo/utils/menu/horizontal_tracker.py
todo/utils/menu/vertical_tracker.py
td_cli-2.3.0.dist-info/METADATA
td_cli-2.3.0.dist-info/WHEEL
td_cli-2.3.0.dist-info/entry_points.txt
td_cli-2.3.0.dist-info/top_level.txt
td_cli-2.3.0.dist-info/RECORD
